auto_proto/__init__.py
auto_proto/auto_proto.py
auto_proto/version.py
auto_proto-0.6.data/data/share/auto_proto/README.rst
auto_proto-0.6.dist-info/LICENSE
auto_proto-0.6.dist-info/METADATA
auto_proto-0.6.dist-info/WHEEL
auto_proto-0.6.dist-info/top_level.txt
auto_proto-0.6.dist-info/RECORD
