Metadata-Version: 2.1
Name: auto-proto
Version: 0.6
Summary: Automated protocol buffer generation from examples.
Home-page: https://github.com/aagnone3/auto-proto
Author: Anthony Agnone
Author-email: anthonyagnone@gmail.com
License: UNKNOWN
Platform: UNKNOWN
Classifier: Development Status :: 3 - Alpha
Classifier: Programming Language :: Python :: 3
Classifier: Topic :: Scientific/Engineering
Requires-Dist: pandas
Requires-Dist: numpy
Requires-Dist: protobuf
